AUTHORS.txt
LICENSE.txt
MANIFEST.in
README.rst
setup.py
boing/__init__.py
boing/run.py
boing.egg-info/PKG-INFO
boing.egg-info/SOURCES.txt
boing.egg-info/dependency_links.txt
boing.egg-info/entry_points.txt
boing.egg-info/requires.txt
boing.egg-info/top_level.txt
boing/core/StateMachine.py
boing/core/__init__.py
boing/core/economy.py
boing/core/graph.py
boing/core/observer.py
boing/core/querypath.py
boing/filtering/__init__.py
boing/filtering/filter/ExponentialFilter.py
boing/filtering/filter/KalmanFilter.py
boing/filtering/filter/MovingWindowFilter.py
boing/filtering/filter/OneEuroFilter.py
boing/filtering/filter/__init__.py
boing/filtering/noise/NoiseFunctor.py
boing/filtering/noise/PerlinNoise.py
boing/filtering/noise/__init__.py
boing/gesture/__init__.py
boing/gesture/rubine.py
boing/gesture/utils.py
boing/net/__init__.py
boing/net/bytes.py
boing/net/ip.py
boing/net/json.py
boing/net/ntp.py
boing/net/osc.py
boing/net/pickle.py
boing/net/slip.py
boing/net/tcp.py
boing/net/tuio.py
boing/net/udp.py
boing/nodes/__init__.py
boing/nodes/encoding.py
boing/nodes/filtering.py
boing/nodes/ioport.py
boing/nodes/loader.py
boing/nodes/logger.py
boing/nodes/uiRecorder.py
boing/nodes/uiRecorder.ui
boing/nodes/multitouch/ContactViz.py
boing/nodes/multitouch/__init__.py
boing/nodes/player/__init__.py
boing/nodes/player/gui.py
boing/nodes/player/playlist.py
boing/nodes/player/uiPlayer.py
boing/nodes/player/uiPlayer.ui
boing/nodes/player/icons/file-not_valid.png
boing/nodes/player/icons/file.png
boing/nodes/player/icons/folder.png
boing/nodes/player/icons/loop.png
boing/nodes/player/icons/play.png
boing/nodes/player/icons/stop.png
boing/test/__init__.py
boing/test/run.py
boing/test/core/__init__.py
boing/test/core/test_StateMachine.py
boing/test/core/test_economy.py
boing/test/core/test_observer.py
boing/test/filtering/__init__.py
boing/test/filtering/test_filter.py
boing/test/gesture/__init__.py
boing/test/gesture/test_rubine.py
boing/test/net/__init__.py
boing/test/net/test__init__.py
boing/test/net/test_json.py
boing/test/net/test_osc.py
boing/test/net/test_pickle.py
boing/test/net/test_slip.py
boing/test/net/test_tcp.py
boing/test/net/test_udp.py
