Metadata-Version: 1.0
Name: boing
Version: 0.3.1
Summary: Boing is a toolkit designed to support the development
